MANIFEST.in
README.txt
setup.cfg
setup.py
collective/__init__.py
collective.phantasy.egg-info/PKG-INFO
collective.phantasy.egg-info/SOURCES.txt
collective.phantasy.egg-info/dependency_links.txt
collective.phantasy.egg-info/entry_points.txt
collective.phantasy.egg-info/namespace_packages.txt
collective.phantasy.egg-info/not-zip-safe
collective.phantasy.egg-info/requires.txt
collective.phantasy.egg-info/top_level.txt
collective/phantasy/__init__.py
collective/phantasy/atfolderskinnable.zcml
collective/phantasy/config.py
collective/phantasy/configure.zcml
collective/phantasy/integration.txt
collective/phantasy/minimal.zcml
collective/phantasy/profiles.zcml
collective/phantasy/setuphandlers.py
collective/phantasy/widget.py
collective/phantasy/atphantasy/README.txt
collective/phantasy/atphantasy/__init__.py
collective/phantasy/atphantasy/configure.zcml
collective/phantasy/atphantasy/permissions.py
collective/phantasy/atphantasy/browser/__init__.py
collective/phantasy/atphantasy/browser/atphantasy_view.py
collective/phantasy/atphantasy/browser/configure.zcml
collective/phantasy/atphantasy/browser/folderskinview.py
collective/phantasy/atphantasy/browser/interfaces.py
collective/phantasy/atphantasy/browser/templates/phantasyskin_import.pt
collective/phantasy/atphantasy/browser/templates/phantasyskin_view.pt
collective/phantasy/atphantasy/content/__init__.py
collective/phantasy/atphantasy/content/file.py
collective/phantasy/atphantasy/content/image.py
collective/phantasy/atphantasy/content/phantasyschema.py
collective/phantasy/atphantasy/content/skin.py
collective/phantasy/atphantasy/content/skinsrepository.py
collective/phantasy/atphantasy/extendcontents/__init__.py
collective/phantasy/atphantasy/extendcontents/configure.zcml
collective/phantasy/atphantasy/extendcontents/skinextension.py
collective/phantasy/atphantasy/interfaces/__init__.py
collective/phantasy/atphantasy/interfaces/file.py
collective/phantasy/atphantasy/interfaces/image.py
collective/phantasy/atphantasy/interfaces/skin.py
collective/phantasy/atphantasy/interfaces/skinsrepository.py
collective/phantasy/browser/__init__.py
collective/phantasy/browser/configure.zcml
collective/phantasy/browser/interfaces.py
collective/phantasy/browser/phantasy_properties.py
collective/phantasy/browser/viewlets.py
collective/phantasy/browser/css/collective.phantasy.css.dtml
