Metadata-Version: 1.1
Name: collective.phantasy
Version: 2.6
Summary: dynamic theme for Plone
Home-page: http://plone.org/products/collective-phantasy
Author: Jean-mat Grimaldi & Gilles Lenfant's good advice and moral support
Author-email: jeanmat.grimaldi@gmail.com
License: GPL
Keywords: theme skin dynamic-skin
Platform: UNKNOWN
Classifier: Framework :: Plone
Classifier: Programming Language :: Python
Classifier: Topic :: Software Development :: Libraries :: Python Modules
